helga_xkcd/__init__.py
helga_xkcd/client.py
helga_xkcd/command.py
helga_xkcd/db.py
helga_xkcd-0.1.2.dist-info/DESCRIPTION.rst
helga_xkcd-0.1.2.dist-info/entry_points.txt
helga_xkcd-0.1.2.dist-info/METADATA
helga_xkcd-0.1.2.dist-info/metadata.json
helga_xkcd-0.1.2.dist-info/RECORD
helga_xkcd-0.1.2.dist-info/top_level.txt
helga_xkcd-0.1.2.dist-info/WHEEL
helga_xkcd-0.1.2.dist-info/zip-safe
