Metadata-Version: 2.0
Name: helga-xkcd
Version: 0.1.2
Summary: A helga plugin to fetch xkcd comics
Home-page: https://github.com/crlane/helga-xkcd
Author: Cameron Lane
Author-email: crlane@adamanteus.com
License: UNKNOWN
Platform: UNKNOWN
Classifier: Development Status :: 4 - Beta
Classifier: Topic :: Communications :: Chat :: Internet Relay Chat
Classifier: Framework :: Twisted
Classifier: License :: OSI Approved :: MIT License
Classifier: Operating System :: OS Independent
Classifier: Programming Language :: Python
Classifier: Programming Language :: Python :: 2
Classifier: Programming Language :: Python :: 2.6
Classifier: Programming Language :: Python :: 2.7
Classifier: Topic :: Software Development :: Libraries :: Python Modules
Requires-Dist: helga
Requires-Dist: requests
Provides-Extra: development
Requires-Dist: ipython (<6.0); extra == 'development'
Requires-Dist: twine; extra == 'development'
Requires-Dist: wheel; extra == 'development'
Provides-Extra: testing
Requires-Dist: pytest; extra == 'testing'
Requires-Dist: coverage; extra == 'testing'
Requires-Dist: pytest-cov; extra == 'testing'
Requires-Dist: mock; extra == 'testing'
